setup.py
mytest_gameoflife/mytest_gameoflife.py
mytest_gameoflife.egg-info/PKG-INFO
mytest_gameoflife.egg-info/SOURCES.txt
mytest_gameoflife.egg-info/dependency_links.txt
mytest_gameoflife.egg-info/not-zip-safe
mytest_gameoflife.egg-info/top_level.txt