Metadata-Version: 1.0
Name: mytest-gameoflife
Version: 0.0.1
Summary: This is a project for the course Advanced Scientific Programming in Python - Uppsala University
Home-page: https://github.com/wangd3109/mytest_gameoflife
Author: Duo Wang
Author-email: wangd3109@gmail.com
License: MIT
Platform: UNKNOWN
